setup.py
tcpping2/__init__.py
tcpping2/test_tcpping.py
tcpping2.egg-info/PKG-INFO
tcpping2.egg-info/SOURCES.txt
tcpping2.egg-info/dependency_links.txt
tcpping2.egg-info/top_level.txt